hr_tool_logic/__init__.py
hr_tool_logic/candidate.py
hr_tool_logic/candidate_repository.py
hr_tool_logic/interview.py
hr_tool_logic/interview_repository.py
hr_tool_logic/interviewer.py
hr_tool_logic/interviewer_repository.py
hr_tool_logic/interviewround.py
hr_tool_logic/interviewround_repository.py
hr_tool_logic/repository.py
hr_tool_logic-0.0.2.dist-info/METADATA
hr_tool_logic-0.0.2.dist-info/WHEEL
hr_tool_logic-0.0.2.dist-info/top_level.txt
hr_tool_logic-0.0.2.dist-info/RECORD
