Metadata-Version: 2.1
Name: hr_tool_logic
Version: 0.0.2
Summary: My first Python package
Author: Ну я
Author-email: <youremail@email.com>
